async_casbin_adapter/__init__.py
async_casbin_adapter/adapter.py
async_casbin_adapter/apps.py
async_casbin_adapter/enforcer.py
async_casbin_adapter/models.py
async_casbin_adapter/utils.py
async_casbin_adapter/migrations/0001_initial.py
async_casbin_adapter/migrations/__init__.py
casbin_async_django_orm_adapter-1.1.0.dist-info/licenses/LICENSE
node_modules/npm/node_modules/node-gyp/gyp/gyp_main.py
node_modules/npm/node_modules/node-gyp/gyp/test_gyp.py
node_modules/npm/node_modules/node-gyp/gyp/pylib/gyp/MSVSNew.py
node_modules/npm/node_modules/node-gyp/gyp/pylib/gyp/MSVSProject.py
node_modules/npm/node_modules/node-gyp/gyp/pylib/gyp/MSVSSettings.py
node_modules/npm/node_modules/node-gyp/gyp/pylib/gyp/MSVSSettings_test.py
node_modules/npm/node_modules/node-gyp/gyp/pylib/gyp/MSVSToolFile.py
node_modules/npm/node_modules/node-gyp/gyp/pylib/gyp/MSVSUserFile.py
node_modules/npm/node_modules/node-gyp/gyp/pylib/gyp/MSVSUtil.py
node_modules/npm/node_modules/node-gyp/gyp/pylib/gyp/MSVSVersion.py
node_modules/npm/node_modules/node-gyp/gyp/pylib/gyp/__init__.py
node_modules/npm/node_modules/node-gyp/gyp/pylib/gyp/common.py
node_modules/npm/node_modules/node-gyp/gyp/pylib/gyp/common_test.py
node_modules/npm/node_modules/node-gyp/gyp/pylib/gyp/easy_xml.py
node_modules/npm/node_modules/node-gyp/gyp/pylib/gyp/easy_xml_test.py
node_modules/npm/node_modules/node-gyp/gyp/pylib/gyp/flock_tool.py
node_modules/npm/node_modules/node-gyp/gyp/pylib/gyp/input.py
node_modules/npm/node_modules/node-gyp/gyp/pylib/gyp/input_test.py
node_modules/npm/node_modules/node-gyp/gyp/pylib/gyp/mac_tool.py
node_modules/npm/node_modules/node-gyp/gyp/pylib/gyp/msvs_emulation.py
node_modules/npm/node_modules/node-gyp/gyp/pylib/gyp/ninja_syntax.py
node_modules/npm/node_modules/node-gyp/gyp/pylib/gyp/simple_copy.py
node_modules/npm/node_modules/node-gyp/gyp/pylib/gyp/win_tool.py
node_modules/npm/node_modules/node-gyp/gyp/pylib/gyp/xcode_emulation.py
node_modules/npm/node_modules/node-gyp/gyp/pylib/gyp/xcode_emulation_test.py
casbin_async_django_orm_adapter-1.1.0.dist-info/METADATA
casbin_async_django_orm_adapter-1.1.0.dist-info/WHEEL
casbin_async_django_orm_adapter-1.1.0.dist-info/top_level.txt
casbin_async_django_orm_adapter-1.1.0.dist-info/RECORD
