Metadata-Version: 2.4
Name: casbin-async-django-orm-adapter
Version: 1.1.0
Summary: Async Django ORM adapter for PyCasbin
Author-email: Yang Luo <hsluoyz@qq.com>
License: Apache 2.0
Project-URL: Home-page, https://github.com/officialpycasbin/async-django-orm-adapter
Keywords: async,pycasbin,casbin,adapter,storage-driver,django,orm,django-orm,access-control,authorization
Classifier: Programming Language :: Python :: 3.9
Classifier: Programming Language :: Python :: 3.10
Classifier: Programming Language :: Python :: 3.11
Classifier: Programming Language :: Python :: 3.12
Classifier: License :: OSI Approved :: Apache Software License
Classifier: Operating System :: OS Independent
Requires-Python: >=3.7
License-File: LICENSE
Requires-Dist: pycasbin>=2.0.0
Requires-Dist: Django
Dynamic: license-file
